{
"type": "FeatureCollection",
"name": "geo_26_地域密着型特定施設入居者生活介護（有料老人ホーム（サービス付き高齢者向け住宅））",
"crs": { "type": "name", "properties": { "name": "urn:ogc:def:crs:OGC:1.3:CRS84" } },
"features": [
{ "type": "Feature", "properties": { "内容": "二軒茶屋翔裕館【地域密着型特定施設入居者生活介護（有料老人ホーム（サービス付き高齢者向け住宅））】静市市原町705-1二軒茶屋翔裕館", "url": "https://www.kaigokensaku.mhlw.go.jp/26/index.php?action_kouhyou_detail_004_kani=true&JigyosyoCd=2690600289-00&ServiceCd=&Type=search", "url2": "https://www.sanga-kaigo.co.jp" }, "geometry": { "type": "Point", "coordinates": [ 135.7628091, 35.0749907 ] } },
{ "type": "Feature", "properties": { "内容": "ハーモニーこがなの家【地域密着型特定施設入居者生活介護（有料老人ホーム（サービス付き高齢者向け住宅））】久我石原町１－４１", "url": "https://www.kaigokensaku.mhlw.go.jp/26/index.php?action_kouhyou_detail_004_kani=true&JigyosyoCd=2690900101-00&ServiceCd=&Type=search", "url2": "http://www.kurashino-harmony.or.jp" }, "geometry": { "type": "Point", "coordinates": [ 135.733007, 34.9463615 ] } },
{ "type": "Feature", "properties": { "内容": "なぎつじ翔裕館Ⅰ号館【地域密着型特定施設入居者生活介護（有料老人ホーム（サービス付き高齢者向け住宅））】京都府京都市山科区椥辻封シ川町43－2なぎつじ翔裕館Ⅰ号館", "url": "https://www.kaigokensaku.mhlw.go.jp/26/index.php?action_kouhyou_detail_004_kani=true&JigyosyoCd=2694100336-00&ServiceCd=&Type=search", "url2": "http://sangajapan.jp" }, "geometry": { "type": "Point", "coordinates": [ 135.810217099999988, 34.9735292 ] } },
{ "type": "Feature", "properties": { "内容": "西京都病院　ｻｰﾋﾞｽ付き高齢者向け住宅　桂寿の郷【地域密着型特定施設入居者生活介護（有料老人ホーム（サービス付き高齢者向け住宅））】京都市西京区川島権田町36-1", "url": "https://www.kaigokensaku.mhlw.go.jp/26/index.php?action_kouhyou_detail_004_kani=true&JigyosyoCd=2694000288-00&ServiceCd=&Type=search", "url2": "http://www.hospynkh.jp/keiju/" }, "geometry": { "type": "Point", "coordinates": [ 135.696752599999968, 34.978855 ] } }
]
}
