{
"type": "FeatureCollection",
"name": "geo_26_介護療養型医療施設",
"crs": { "type": "name", "properties": { "name": "urn:ogc:def:crs:OGC:1.3:CRS84" } },
"features": [
{ "type": "Feature", "properties": { "内容": "医療法人新生十全会京都東山老年サナトリウム【介護療養型医療施設】京都市山科区日ノ岡夷谷町11番地", "url": "https://www.kaigokensaku.mhlw.go.jp/26/index.php?action_kouhyou_detail_004_kani=true&JigyosyoCd=2614100069-00&ServiceCd=530&Type=search", "url2": "http://www.juzenkai.or.jp" }, "geometry": { "type": "Point", "coordinates": [ 135.795095225270074, 35.000730351030491 ] } }
]
}
